{
  "users": [
    {
      "id": 1,
      "email": "json-server",
      "password": "123",
      "username": "test"
    },
    {
      "email": "pawel@gmail.com",
      "username": "pawel",
      "password": "1234",
      "id": 2
    },
    {
      "email": "pawel1@gmail.com",
      "username": "pawel1",
      "password": "password",
      "id": 3
    }
  ],
  "clients": [
    {
      "firstname": "Test",
      "surename": "Testowy",
      "email": "test@gmail.com",
      "address": "Miasto ul: Testowa 12",
      "postcode": "11-111",
      "id": 1
    },
    {
      "firstname": "Test12",
      "surename": "Testowy11",
      "email": "test3@gmail.com",
      "address": "Miasto ul: Testowa 12",
      "postcode": "11-111",
      "id": 3
    },
    {
      "firstname": "Paweł",
      "surename": "Andrzej",
      "email": "adrzejpawel@gmail.com",
      "address": "Wrocław Krzycka 12",
      "postcode": "53-112",
      "id": 4
    },
    {
      "firstname": "Grzegorz",
      "surename": "Nazwisko",
      "email": "Super@adre.com",
      "address": "Jakaś ulica",
      "postcode": "12-123",
      "id": 5
    }
  ]
}